pixie/__init__.py
pixie/_version.py
pixie/codegen_helpers.py
pixie/compiler.py
pixie/compiler_lock.py
pixie/cpus.py
pixie/llvm_types.py
pixie/overlay.py
pixie/platform.py
pixie/pyapi.py
pixie/types.py
numba_pixie-0.0.1.dev0.dist-info/LICENSE
numba_pixie-0.0.1.dev0.dist-info/LICENSES.third-party
numba_pixie-0.0.1.dev0.dist-info/METADATA
numba_pixie-0.0.1.dev0.dist-info/WHEEL
numba_pixie-0.0.1.dev0.dist-info/top_level.txt
numba_pixie-0.0.1.dev0.dist-info/RECORD
